jk_licenses/License.py
jk_licenses/LicenseMgr.py
jk_licenses/VariableDef.py
jk_licenses/__init__.py
jk_licenses/licenses/License_0BSD.json
jk_licenses/licenses/License_0BSD.txt
jk_licenses/licenses/License_AGPLv3.json
jk_licenses/licenses/License_AGPLv3.txt
jk_licenses/licenses/License_AGPLv3_notes.txt
jk_licenses/licenses/License_Apache2.json
jk_licenses/licenses/License_Apache2.txt
jk_licenses/licenses/License_Apache2_notes.txt
jk_licenses/licenses/License_BSD2.json
jk_licenses/licenses/License_BSD2.txt
jk_licenses/licenses/License_BSD3.json
jk_licenses/licenses/License_BSD3.txt
jk_licenses/licenses/License_GPLv3.json
jk_licenses/licenses/License_GPLv3.txt
jk_licenses/licenses/License_GPLv3_notes.txt
jk_licenses/licenses/License_LGPLv3.json
jk_licenses/licenses/License_LGPLv3.txt
jk_licenses/licenses/License_MIT.json
jk_licenses/licenses/License_MIT.txt
jk_licenses/licenses/License_Proprietary.json
jk_licenses/licenses/License_Proprietary.txt
jk_licenses-0.2024.8.4.dist-info/WHEEL
jk_licenses-0.2024.8.4.dist-info/METADATA
jk_licenses-0.2024.8.4.dist-info/RECORD
