Metadata-Version: 2.1
Name: jk_licenses
Version: 0.2024.8.4
Summary: This python module provides OS licenses. This module is intended as a building block in module/package/application management.
Keywords: 
Author-email: Jürgen Knauth <pubsrc@binary-overflow.de>
Maintainer-email: Jürgen Knauth <pubsrc@binary-overflow.de>
Requires-Python: >=3.8
Classifier: Development Status :: 5 - Production/Stable
Classifier: License :: OSI Approved :: Apache Software License
Classifier: Programming Language :: Python :: 3
Requires-Dist: jk_typing
Requires-Dist: jk_json
